<PAMDataset>
  <Metadata>
    <MDI key="DataType">Generic</MDI>
  </Metadata>
  <PAMRasterBand band="1">
    <Histograms>
      <HistItem>
        <HistMin>-3.793295999999999</HistMin>
        <HistMax>12.330085</HistMax>
        <BucketCount>256</BucketCount>
        <IncludeOutOfRange>1</IncludeOutOfRange>
        <Approximate>0</Approximate>
        <HistCounts>3|0|3|4|4|10|446|789|1098|3827|2603|4006|7793590|744|402|574|374|655|286|564|290|265|712|230|635|311|221|498|298|225|405|298|140|378|263|144|459|295|257|516|342|343|501|348|344|746|435|940|906|729|871|1006|1476|2191|3659|4427|13397|14298|21147|15687673|34487|10016|7291|8171|5471|4301|3528|3741|2945|3544|3393|3062|3856|3419|3953|46654|10353|4697|2174|1750|2400|1628|1703|2084|1755|1815|2429|1702|1941|2238|1853|1612|2019|1833|1891|2306|1855|2671|2095|2405|2522|2403|3253|2528|4040|3159|4627|584532|14728|11282|13295|5098|3310|2197|939|465|210|146|90|137|82|75|76|77|128|69|77|83|93|227|74|81|55|79|82|61|123|63|85|94|62|73|109|74|79|77|64|59|124|133|72|90|68|61|149|124|77|87|135|80|89|61|92|64|84|69|76|76|115|108|76|75|62|72|73|60|150|140|66|75|75|70|72|118|82|98|127|54|93|120|57|88|103|91|159|105|106|101|63|94|104|174|72|100|71|99|98|151|173|111|107|166|94|213|188|142|155|1351|42685|781|686|722|549|515|579|552|656|299|526|559|308|165|186|111|137|126|117|95|69|58|44|44|28|16|14|22|13|7|6|2|7|0|2|0|1|1</HistCounts>
      </HistItem>
      <HistItem>
        <HistMin>-3.653730000000001</HistMin>
        <HistMax>12.341536171875</HistMax>
        <BucketCount>256</BucketCount>
        <IncludeOutOfRange>1</IncludeOutOfRange>
        <Approximate>0</Approximate>
        <HistCounts>5|2|6|45|542|817|2105|2926|2996|4048|7792951|736|392|551|427|616|268|593|293|231|702|229|644|303|220|494|299|225|406|300|148|382|233|168|471|262|266|506|317|336|499|340|362|748|389|907|782|782|1024|924|1410|1922|3129|4315|10896|14115|17123|31390|15705554|10309|7626|8932|4834|5146|3554|3575|3136|3427|3508|3093|3829|3193|3513|4260|51935|6897|3119|2012|1679|2271|1714|1588|2044|1766|1572|2354|1687|1805|2130|1849|1977|1533|2004|2341|1770|2064|2282|2084|2942|2225|2547|3250|2786|3812|4233|11598|571971|12770|11686|11567|3625|3112|1607|750|413|192|109|98|151|69|63|103|63|140|85|86|60|77|226|76|63|65|81|73|92|66|70|92|62|65|69|110|71|82|63|74|55|143|121|67|82|63|70|95|102|79|70|111|78|87|58|96|60|90|75|65|84|105|102|66|68|60|59|74|76|132|164|80|54|89|69|86|100|76|93|144|70|67|141|74|81|88|98|149|80|92|76|74|73|94|191|85|90|81|72|111|138|194|125|104|186|112|131|233|188|152|398|41689|1069|705|676|782|521|525|609|640|495|382|442|520|235|171|174|145|135|119|102|80|74|60|34|36|26|19|12|16|10|5|5|10|4|1|1|0|0|1</HistCounts>
      </HistItem>
    </Histograms>
    <Metadata>
      <MDI key="RepresentationType">ATHEMATIC</MDI>
      <MDI key="STATISTICS_COVARIANCES">2.644971481078949</MDI>
      <MDI key="STATISTICS_EXCLUDEDVALUES"></MDI>
      <MDI key="STATISTICS_MAXIMUM">12.330085</MDI>
      <MDI key="STATISTICS_MEAN">-0.84562870697647</MDI>
      <MDI key="STATISTICS_MEDIAN">-0.062788</MDI>
      <MDI key="STATISTICS_MINIMUM">-3.793296</MDI>
      <MDI key="STATISTICS_SKIPFACTORX">1</MDI>
      <MDI key="STATISTICS_SKIPFACTORY">1</MDI>
      <MDI key="STATISTICS_STDDEV">1.626336828913</MDI>
    </Metadata>
  </PAMRasterBand>
</PAMDataset>
